lazy_services/__init__.py
django_lazy_services-0.0.3.dist-info/LICENSE
django_lazy_services-0.0.3.dist-info/METADATA
django_lazy_services-0.0.3.dist-info/WHEEL
django_lazy_services-0.0.3.dist-info/top_level.txt
django_lazy_services-0.0.3.dist-info/RECORD
