Metadata-Version: 2.1
Name: django-lazy-services
Version: 0.0.3
Summary: A helper for switching between test and production versions of a service module
Home-page: https://github.com/tolomea/django-lazy-services
Author: Gordon Wrigley
Author-email: gordon.wrigley@gmail.com
License: UNKNOWN
Platform: UNKNOWN
Classifier: Programming Language :: Python :: 3
Classifier: License :: OSI Approved :: MIT License
Classifier: Operating System :: OS Independent
Requires-Python: >=3.6
